tinytuya/BulbDevice.py
tinytuya/Cloud.py
tinytuya/CoverDevice.py
tinytuya/OutletDevice.py
tinytuya/__init__.py
tinytuya/__main__.py
tinytuya/scanner.py
tinytuya/wizard.py
tinytuya/Contrib/AtorchTemperatureControllerDevice.py
tinytuya/Contrib/BlanketDevice.py
tinytuya/Contrib/ClimateDevice.py
tinytuya/Contrib/ColorfulX7Device.py
tinytuya/Contrib/DoorbellDevice.py
tinytuya/Contrib/IRRemoteControlDevice.py
tinytuya/Contrib/InverterHeatPumpDevice.py
tinytuya/Contrib/PresenceDetectorDevice.py
tinytuya/Contrib/RFRemoteControlDevice.py
tinytuya/Contrib/SocketDevice.py
tinytuya/Contrib/ThermostatDevice.py
tinytuya/Contrib/WiFiDualMeterDevice.py
tinytuya/Contrib/__init__.py
tinytuya/core/Device.py
tinytuya/core/XenonDevice.py
tinytuya/core/__init__.py
tinytuya/core/command_types.py
tinytuya/core/const.py
tinytuya/core/core.py
tinytuya/core/crypto_helper.py
tinytuya/core/error_helper.py
tinytuya/core/exceptions.py
tinytuya/core/header.py
tinytuya/core/message_helper.py
tinytuya/core/udp_helper.py
tinytuya-1.17.3.dist-info/licenses/LICENSE
tinytuya-1.17.3.dist-info/METADATA
tinytuya-1.17.3.dist-info/WHEEL
tinytuya-1.17.3.dist-info/entry_points.txt
tinytuya-1.17.3.dist-info/top_level.txt
tinytuya-1.17.3.dist-info/RECORD
