Metadata-Version: 2.4
Name: tinytuya
Version: 1.17.3
Summary: Python module to interface with Tuya WiFi smart devices
Home-page: https://github.com/jasonacox/tinytuya
Author: Jason Cox
Author-email: jason@jasonacox.com
Classifier: Programming Language :: Python :: 3
Classifier: License :: OSI Approved :: MIT License
Classifier: Operating System :: OS Independent
License-File: LICENSE
Requires-Dist: requests
Requires-Dist: colorama
Requires-Dist: cryptography
Dynamic: author
Dynamic: author-email
Dynamic: classifier
Dynamic: description
Dynamic: description-content-type
Dynamic: home-page
Dynamic: license-file
Dynamic: requires-dist
Dynamic: summary
